arclet/cithun/__init__.py
arclet/cithun/async_/__init__.py
arclet/cithun/async_/function.py
arclet/cithun/async_/service.py
arclet/cithun/async_/store.py
arclet/cithun/async_/strategy.py
arclet/cithun/builtins/__init__.py
arclet/cithun/builtins/attach.py
arclet/cithun/builtins/database.py
arclet/cithun/builtins/json.py
arclet/cithun/config.py
arclet/cithun/exceptions.py
arclet/cithun/function.py
arclet/cithun/model.py
arclet/cithun/service.py
arclet/cithun/store.py
arclet/cithun/strategy.py
arclet_cithun-1.3.0.dist-info/METADATA
arclet_cithun-1.3.0.dist-info/WHEEL
arclet_cithun-1.3.0.dist-info/entry_points.txt
arclet_cithun-1.3.0.dist-info/licenses/LICENSE
arclet_cithun-1.3.0.dist-info/RECORD
