Metadata-Version: 2.1
Name: arclet-cithun
Version: 1.3.0
Summary: A permission system modeled on the file permission system under Unix.
Author-Email: RF-Tar-Railt <rf_tar_railt@qq.com>
License: MIT
Requires-Python: >=3.10
